pycryp/__init__.py
pycryp/decrypt.py
pycryp/encrypt.py
pycryp/passwords.py
pycryp/salt.py
test/__init__.py
test/test_decrypt.py
test/test_encrypt.py
test/test_passwords.py
test/test_salt.py
pycryp-0.2.1.dist-info/AUTHORS.md
pycryp-0.2.1.dist-info/LICENSE
pycryp-0.2.1.dist-info/METADATA
pycryp-0.2.1.dist-info/WHEEL
pycryp-0.2.1.dist-info/top_level.txt
pycryp-0.2.1.dist-info/RECORD
