Metadata-Version: 2.1
Name: pycryp
Version: 0.2.1
Summary: package to encrypt and decrypt messages
Home-page: https://github.com/suvanbanerjee/pycryp
Author: Suvan Banerjee
Author-email: <banerjeesuvan@gmail.com>
Keywords: python,aes,encryption,decryption,aes-256-cbc
Classifier: Development Status :: 4 - Beta
Classifier: Intended Audience :: Developers
Classifier: Programming Language :: Python :: 3
Classifier: License :: OSI Approved :: MIT License
Classifier: Operating System :: OS Independent
Requires-Python: >=3.5
License-File: LICENSE
License-File: AUTHORS.md
Requires-Dist: cryptography
